cgmes2pgm_converter/__init__.py
cgmes2pgm_converter/converter.py
cgmes2pgm_converter/common/__init__.py
cgmes2pgm_converter/common/cgmes_dataset.py
cgmes2pgm_converter/common/cgmes_literals.py
cgmes2pgm_converter/common/converter_literals.py
cgmes2pgm_converter/common/converter_options.py
cgmes2pgm_converter/common/id_mapper.py
cgmes2pgm_converter/common/measurement_substitution.py
cgmes2pgm_converter/common/network_splitting.py
cgmes2pgm_converter/common/pgm_literals.py
cgmes2pgm_converter/common/sparql_datasource.py
cgmes2pgm_converter/common/timer.py
cgmes2pgm_converter/common/topology.py
cgmes2pgm_converter/common/topology_subnets.py
cgmes2pgm_converter/components/__init__.py
cgmes2pgm_converter/components/component.py
cgmes2pgm_converter/components/node.py
cgmes2pgm_converter/components/appliance/__init__.py
cgmes2pgm_converter/components/appliance/gen_for_dc.py
cgmes2pgm_converter/components/appliance/linear_shunt.py
cgmes2pgm_converter/components/appliance/nonlinear_shunt.py
cgmes2pgm_converter/components/appliance/source.py
cgmes2pgm_converter/components/appliance/source_from_island.py
cgmes2pgm_converter/components/appliance/sym_gen.py
cgmes2pgm_converter/components/appliance/sym_load.py
cgmes2pgm_converter/components/branch/__init__.py
cgmes2pgm_converter/components/branch/equivalent_branch.py
cgmes2pgm_converter/components/branch/gb_from_link.py
cgmes2pgm_converter/components/branch/line.py
cgmes2pgm_converter/components/branch/link.py
cgmes2pgm_converter/components/branch/transformer/__init__.py
cgmes2pgm_converter/components/branch/transformer/abstract_transformer.py
cgmes2pgm_converter/components/branch/transformer/abstract_two_2_transformer.py
cgmes2pgm_converter/components/branch/transformer/three_w_pst_as_genb.py
cgmes2pgm_converter/components/branch/transformer/three_w_pst_aux_node.py
cgmes2pgm_converter/components/branch/transformer/three_w_transformer_as_genb.py
cgmes2pgm_converter/components/branch/transformer/three_w_transformer_aux_node.py
cgmes2pgm_converter-0.4.3.dist-info/licenses/LICENSE
cgmes2pgm_converter-0.4.3.dist-info/METADATA
cgmes2pgm_converter-0.4.3.dist-info/WHEEL
cgmes2pgm_converter-0.4.3.dist-info/top_level.txt
cgmes2pgm_converter-0.4.3.dist-info/RECORD
